Metadata-Version: 1.1
Name: grabicon
Version: 0.1.1
Summary: grab all favicons attached to a webpage by url
Home-page: http://github.com/dsfx3d/grabicon
Author: dsfx3d
Author-email: dsfx3d@gmail.com
License: MIT
Platform: UNKNOWN
Classifier: Development Status :: 4 - Beta
Classifier: License :: OSI Approved :: MIT License
Classifier: Programming Language :: Python :: 3
Classifier: Intended Audience :: Developers
Classifier: Topic :: Internet :: WWW/HTTP
